monoplane/__init__.py
monoplane/cli.py
monoplane-0.1.1.dist-info/LICENSE
monoplane-0.1.1.dist-info/METADATA
monoplane-0.1.1.dist-info/WHEEL
monoplane-0.1.1.dist-info/entry_points.txt
monoplane-0.1.1.dist-info/RECORD
