Metadata-Version: 2.1
Name: monoplane
Version: 0.1.1
Summary: Monoplane is a tiny tool designed to help you run multiple processes in your local development environment. Especially useful for monorepos.
Home-page: https://github.com/yegortokmakov/monoplane
License: MIT
Keywords: monorepo,development,local
Author: Yegor Tokmakov
Author-email: yegor@tokmakov.biz
Requires-Python: >=3.10,<4.0
Classifier: License :: OSI Approved :: MIT License
Classifier: Programming Language :: Python :: 3
Classifier: Programming Language :: Python :: 3.10
Classifier: Programming Language :: Python :: 3.11
Classifier: Programming Language :: Python :: 3.12
Requires-Dist: PyYAML (>=6.0.1,<7.0.0)
Requires-Dist: psutil (>=5.9.8,<6.0.0)
Requires-Dist: readchar (>=4.0.5,<5.0.0)
Requires-Dist: tabulate (>=0.9.0,<0.10.0)
Project-URL: Bug Tracker, https://github.com/yegortokmakov/monoplane/issues
Project-URL: Repository, https://github.com/yegortokmakov/monoplane
